{
	"$schema": "http://schema.management.azure.com/schemas/2015-01-01/deploymentTemplate.json#",
	"contentVersion": "1.0.0.0",
	"parameters": {
		"factoryName": {
			"type": "string",
			"metadata": "Data Factory name",
			"defaultValue": "jyodatafactory"
		},
		"FileServer5_password": {
			"type": "secureString",
			"metadata": "Secure string for 'password' of 'FileServer5'"
		},
		"FileServer6_password": {
			"type": "secureString",
			"metadata": "Secure string for 'password' of 'FileServer6'"
		},
		"OnPrimisesSQL_connectionString": {
			"type": "secureString",
			"metadata": "Secure string for 'connectionString' of 'OnPrimisesSQL'"
		},
		"OnPrimisesSQL_password": {
			"type": "secureString",
			"metadata": "Secure string for 'password' of 'OnPrimisesSQL'"
		},
		"On_premisejyo_password": {
			"type": "secureString",
			"metadata": "Secure string for 'password' of 'On_premisejyo'"
		},
		"metadatafile_password": {
			"type": "secureString",
			"metadata": "Secure string for 'password' of 'metadatafile'"
		},
		"FileServer5_properties_typeProperties_host": {
			"type": "string",
			"defaultValue": "D:\\jyo\\azure data engineer\\data"
		},
		"FileServer5_properties_typeProperties_userId": {
			"type": "string",
			"defaultValue": "desktop-ff8cp36\\dell"
		},
		"FileServer6_properties_typeProperties_host": {
			"type": "string",
			"defaultValue": "D:\\jyo\\azure data engineer\\data"
		},
		"FileServer6_properties_typeProperties_userId": {
			"type": "string",
			"defaultValue": "desktop-ff8cp36\\dell"
		},
		"FileServer7_properties_typeProperties_host": {
			"type": "string",
			"defaultValue": "@{linkedService().hostnamelink}"
		},
		"FileServer7_properties_typeProperties_userId": {
			"type": "string",
			"defaultValue": "@{linkedService().usernamelink}"
		},
		"Link_Lookup_Incremental_properties_typeProperties_host": {
			"type": "string",
			"defaultValue": "D:\\jyo\\azure data engineer\\data\\config_files_for_incre_load"
		},
		"Link_Lookup_Incremental_properties_typeProperties_userId": {
			"type": "string",
			"defaultValue": "@{linkedService().username}"
		},
		"OnPrimisesSQL_properties_typeProperties_userName": {
			"type": "string",
			"defaultValue": "desktop-ff8cp36\\dell"
		},
		"On_premisejyo_properties_typeProperties_host": {
			"type": "string",
			"defaultValue": "D:\\jyo\\azure data engineer"
		},
		"On_premisejyo_properties_typeProperties_userId": {
			"type": "string",
			"defaultValue": "desktop-ff8cp36\\dell"
		},
		"metadatafile_properties_typeProperties_host": {
			"type": "string",
			"defaultValue": "D:\\jyo\\azure data engineer\\data"
		},
		"metadatafile_properties_typeProperties_userId": {
			"type": "string",
			"defaultValue": "desktop-ff8cp36\\dell"
		}
	},
	"variables": {
		"factoryId": "[concat('Microsoft.DataFactory/factories/', parameters('factoryName'))]"
	},
	"resources": [
		{
			"name": "[concat(parameters('factoryName'), '/FileServer5')]",
			"type": "Microsoft.DataFactory/factories/linkedServices",
			"apiVersion": "2018-06-01",
			"properties": {
				"annotations": [],
				"type": "FileServer",
				"typeProperties": {
					"host": "[parameters('FileServer5_properties_typeProperties_host')]",
					"userId": "[parameters('FileServer5_properties_typeProperties_userId')]",
					"password": {
						"type": "SecureString",
						"value": "[parameters('FileServer5_password')]"
					}
				},
				"connectVia": {
					"referenceName": "jyo-IR",
					"type": "IntegrationRuntimeReference"
				}
			},
			"dependsOn": []
		},
		{
			"name": "[concat(parameters('factoryName'), '/FileServer6')]",
			"type": "Microsoft.DataFactory/factories/linkedServices",
			"apiVersion": "2018-06-01",
			"properties": {
				"annotations": [],
				"type": "FileServer",
				"typeProperties": {
					"host": "[parameters('FileServer6_properties_typeProperties_host')]",
					"userId": "[parameters('FileServer6_properties_typeProperties_userId')]",
					"password": {
						"type": "SecureString",
						"value": "[parameters('FileServer6_password')]"
					}
				},
				"connectVia": {
					"referenceName": "jyo-IR",
					"type": "IntegrationRuntimeReference"
				}
			},
			"dependsOn": []
		},
		{
			"name": "[concat(parameters('factoryName'), '/FileServer7')]",
			"type": "Microsoft.DataFactory/factories/linkedServices",
			"apiVersion": "2018-06-01",
			"properties": {
				"parameters": {
					"hostnamelink": {
						"type": "string"
					},
					"usernamelink": {
						"type": "string"
					}
				},
				"annotations": [],
				"type": "FileServer",
				"typeProperties": {
					"host": "[parameters('FileServer7_properties_typeProperties_host')]",
					"userId": "[parameters('FileServer7_properties_typeProperties_userId')]",
					"password": {
						"type": "AzureKeyVaultSecret",
						"store": {
							"referenceName": "AzureKeyVault1",
							"type": "LinkedServiceReference"
						},
						"secretName": "onprimisepw"
					}
				},
				"connectVia": {
					"referenceName": "jyo-IR",
					"type": "IntegrationRuntimeReference"
				}
			},
			"dependsOn": []
		},
		{
			"name": "[concat(parameters('factoryName'), '/Link_Lookup_Incremental')]",
			"type": "Microsoft.DataFactory/factories/linkedServices",
			"apiVersion": "2018-06-01",
			"properties": {
				"parameters": {
					"username": {
						"type": "string"
					}
				},
				"annotations": [],
				"type": "FileServer",
				"typeProperties": {
					"host": "[parameters('Link_Lookup_Incremental_properties_typeProperties_host')]",
					"userId": "[parameters('Link_Lookup_Incremental_properties_typeProperties_userId')]",
					"password": {
						"type": "AzureKeyVaultSecret",
						"store": {
							"referenceName": "AzureKeyVault1",
							"type": "LinkedServiceReference"
						},
						"secretName": "onprimisepw"
					}
				},
				"connectVia": {
					"referenceName": "jyo-IR",
					"type": "IntegrationRuntimeReference"
				}
			},
			"dependsOn": []
		},
		{
			"name": "[concat(parameters('factoryName'), '/OnPrimisesSQL')]",
			"type": "Microsoft.DataFactory/factories/linkedServices",
			"apiVersion": "2018-06-01",
			"properties": {
				"annotations": [],
				"type": "SqlServer",
				"typeProperties": {
					"connectionString": "[parameters('OnPrimisesSQL_connectionString')]",
					"userName": "[parameters('OnPrimisesSQL_properties_typeProperties_userName')]",
					"password": {
						"type": "SecureString",
						"value": "[parameters('OnPrimisesSQL_password')]"
					}
				},
				"connectVia": {
					"referenceName": "Jyo-SelfHost",
					"type": "IntegrationRuntimeReference"
				}
			},
			"dependsOn": []
		},
		{
			"name": "[concat(parameters('factoryName'), '/On_premisejyo')]",
			"type": "Microsoft.DataFactory/factories/linkedServices",
			"apiVersion": "2018-06-01",
			"properties": {
				"annotations": [],
				"type": "FileServer",
				"typeProperties": {
					"host": "[parameters('On_premisejyo_properties_typeProperties_host')]",
					"userId": "[parameters('On_premisejyo_properties_typeProperties_userId')]",
					"password": {
						"type": "SecureString",
						"value": "[parameters('On_premisejyo_password')]"
					}
				},
				"connectVia": {
					"referenceName": "Jyo-SelfHost",
					"type": "IntegrationRuntimeReference"
				}
			},
			"dependsOn": []
		},
		{
			"name": "[concat(parameters('factoryName'), '/metadatafile')]",
			"type": "Microsoft.DataFactory/factories/linkedServices",
			"apiVersion": "2018-06-01",
			"properties": {
				"annotations": [],
				"type": "FileServer",
				"typeProperties": {
					"host": "[parameters('metadatafile_properties_typeProperties_host')]",
					"userId": "[parameters('metadatafile_properties_typeProperties_userId')]",
					"password": {
						"type": "SecureString",
						"value": "[parameters('metadatafile_password')]"
					}
				},
				"connectVia": {
					"referenceName": "jyo-IR",
					"type": "IntegrationRuntimeReference"
				}
			},
			"dependsOn": []
		},
		{
			"name": "[concat(parameters('factoryName'), '/AzureSqlTable8')]",
			"type": "Microsoft.DataFactory/factories/datasets",
			"apiVersion": "2018-06-01",
			"properties": {
				"linkedServiceName": {
					"referenceName": "AzureSqlDatabase4",
					"type": "LinkedServiceReference"
				},
				"parameters": {
					"TableName": {
						"type": "string"
					}
				},
				"annotations": [],
				"type": "AzureSqlTable",
				"schema": [],
				"typeProperties": {
					"schema": "dbo",
					"table": {
						"value": "@dataset().TableName",
						"type": "Expression"
					}
				}
			},
			"dependsOn": []
		},
		{
			"name": "[concat(parameters('factoryName'), '/DelimitedText10')]",
			"type": "Microsoft.DataFactory/factories/datasets",
			"apiVersion": "2018-06-01",
			"properties": {
				"linkedServiceName": {
					"referenceName": "On_premisejyo",
					"type": "LinkedServiceReference"
				},
				"annotations": [],
				"type": "DelimitedText",
				"typeProperties": {
					"location": {
						"type": "FileServerLocation",
						"fileName": "customer.txt",
						"folderPath": "data"
					},
					"columnDelimiter": ",",
					"escapeChar": "\\",
					"firstRowAsHeader": true,
					"quoteChar": "\""
				},
				"schema": [
					{
						"type": "String"
					},
					{
						"type": "String"
					},
					{
						"type": "String"
					}
				]
			},
			"dependsOn": [
				"[concat(variables('factoryId'), '/linkedServices/On_premisejyo')]"
			]
		},
		{
			"name": "[concat(parameters('factoryName'), '/DelimitedText12')]",
			"type": "Microsoft.DataFactory/factories/datasets",
			"apiVersion": "2018-06-01",
			"properties": {
				"linkedServiceName": {
					"referenceName": "AzureBlobStorage1",
					"type": "LinkedServiceReference"
				},
				"parameters": {
					"filename": {
						"type": "string"
					}
				},
				"annotations": [],
				"type": "DelimitedText",
				"typeProperties": {
					"location": {
						"type": "AzureBlobStorageLocation",
						"fileName": {
							"value": "@dataset().filename",
							"type": "Expression"
						},
						"container": "archive"
					},
					"columnDelimiter": "|",
					"escapeChar": "\\",
					"firstRowAsHeader": true,
					"quoteChar": "\""
				},
				"schema": []
			},
			"dependsOn": []
		},
		{
			"name": "[concat(parameters('factoryName'), '/DelimitedText13')]",
			"type": "Microsoft.DataFactory/factories/datasets",
			"apiVersion": "2018-06-01",
			"properties": {
				"linkedServiceName": {
					"referenceName": "AzureBlobStorage1",
					"type": "LinkedServiceReference"
				},
				"annotations": [],
				"type": "DelimitedText",
				"typeProperties": {
					"location": {
						"type": "AzureBlobStorageLocation",
						"fileName": "emp1.txt",
						"folderPath": "archivfile",
						"container": "archive"
					},
					"columnDelimiter": ",",
					"escapeChar": "\\",
					"quoteChar": "\""
				},
				"schema": [
					{
						"type": "String"
					}
				]
			},
			"dependsOn": []
		},
		{
			"name": "[concat(parameters('factoryName'), '/DelimitedText14')]",
			"type": "Microsoft.DataFactory/factories/datasets",
			"apiVersion": "2018-06-01",
			"properties": {
				"linkedServiceName": {
					"referenceName": "AzureBlobStorage1",
					"type": "LinkedServiceReference"
				},
				"parameters": {
					"filename1": {
						"type": "string"
					}
				},
				"annotations": [],
				"type": "DelimitedText",
				"typeProperties": {
					"location": {
						"type": "AzureBlobStorageLocation",
						"fileName": {
							"value": "@dataset().filename1",
							"type": "Expression"
						},
						"folderPath": "archivfile",
						"container": "archive"
					},
					"columnDelimiter": ",",
					"escapeChar": "\\",
					"firstRowAsHeader": true,
					"quoteChar": "\""
				},
				"schema": []
			},
			"dependsOn": []
		},
		{
			"name": "[concat(parameters('factoryName'), '/DelimitedText15')]",
			"type": "Microsoft.DataFactory/factories/datasets",
			"apiVersion": "2018-06-01",
			"properties": {
				"linkedServiceName": {
					"referenceName": "AzureBlobStorage1",
					"type": "LinkedServiceReference"
				},
				"parameters": {
					"name": {
						"type": "string"
					}
				},
				"annotations": [],
				"type": "DelimitedText",
				"typeProperties": {
					"location": {
						"type": "AzureBlobStorageLocation",
						"fileName": {
							"value": "@dataset().name",
							"type": "Expression"
						},
						"container": "archive"
					},
					"columnDelimiter": "|",
					"escapeChar": "\\",
					"firstRowAsHeader": true,
					"quoteChar": "\""
				},
				"schema": []
			},
			"dependsOn": []
		},
		{
			"name": "[concat(parameters('factoryName'), '/DelimitedText16')]",
			"type": "Microsoft.DataFactory/factories/datasets",
			"apiVersion": "2018-06-01",
			"properties": {
				"linkedServiceName": {
					"referenceName": "FileServer3",
					"type": "LinkedServiceReference"
				},
				"annotations": [],
				"type": "DelimitedText",
				"typeProperties": {
					"location": {
						"type": "FileServerLocation",
						"fileName": "config.txt"
					},
					"columnDelimiter": ",",
					"escapeChar": "\\",
					"firstRowAsHeader": true,
					"quoteChar": "\""
				},
				"schema": [
					{
						"type": "String"
					},
					{
						"type": "String"
					},
					{
						"type": "String"
					},
					{
						"type": "String"
					}
				]
			},
			"dependsOn": []
		},
		{
			"name": "[concat(parameters('factoryName'), '/DelimitedText17')]",
			"type": "Microsoft.DataFactory/factories/datasets",
			"apiVersion": "2018-06-01",
			"properties": {
				"linkedServiceName": {
					"referenceName": "AzureBlobStorage1",
					"type": "LinkedServiceReference"
				},
				"annotations": [],
				"type": "DelimitedText",
				"typeProperties": {
					"location": {
						"type": "AzureBlobStorageLocation",
						"folderPath": "filefolder",
						"container": "development"
					},
					"columnDelimiter": ",",
					"escapeChar": "\\",
					"firstRowAsHeader": true,
					"quoteChar": "\""
				},
				"schema": []
			},
			"dependsOn": []
		},
		{
			"name": "[concat(parameters('factoryName'), '/DelimitedText18')]",
			"type": "Microsoft.DataFactory/factories/datasets",
			"apiVersion": "2018-06-01",
			"properties": {
				"linkedServiceName": {
					"referenceName": "FileServer3",
					"type": "LinkedServiceReference"
				},
				"annotations": [],
				"type": "DelimitedText",
				"typeProperties": {
					"location": {
						"type": "FileServerLocation",
						"folderPath": "files"
					},
					"columnDelimiter": ",",
					"escapeChar": "\\",
					"firstRowAsHeader": true,
					"quoteChar": "\""
				},
				"schema": []
			},
			"dependsOn": []
		},
		{
			"name": "[concat(parameters('factoryName'), '/DelimitedText19')]",
			"type": "Microsoft.DataFactory/factories/datasets",
			"apiVersion": "2018-06-01",
			"properties": {
				"linkedServiceName": {
					"referenceName": "AzureBlobStorage1",
					"type": "LinkedServiceReference"
				},
				"annotations": [],
				"type": "DelimitedText",
				"typeProperties": {
					"location": {
						"type": "AzureBlobStorageLocation",
						"folderPath": "filefolder/files",
						"container": "development"
					},
					"columnDelimiter": ",",
					"escapeChar": "\\",
					"firstRowAsHeader": true,
					"quoteChar": "\""
				},
				"schema": []
			},
			"dependsOn": []
		},
		{
			"name": "[concat(parameters('factoryName'), '/DelimitedText20')]",
			"type": "Microsoft.DataFactory/factories/datasets",
			"apiVersion": "2018-06-01",
			"properties": {
				"linkedServiceName": {
					"referenceName": "AzureBlobStorage1",
					"type": "LinkedServiceReference"
				},
				"annotations": [],
				"type": "DelimitedText",
				"typeProperties": {
					"location": {
						"type": "AzureBlobStorageLocation",
						"folderPath": "filefolder",
						"container": "development"
					},
					"columnDelimiter": ",",
					"escapeChar": "\\",
					"firstRowAsHeader": true,
					"quoteChar": "\""
				},
				"schema": []
			},
			"dependsOn": []
		},
		{
			"name": "[concat(parameters('factoryName'), '/DelimitedText21')]",
			"type": "Microsoft.DataFactory/factories/datasets",
			"apiVersion": "2018-06-01",
			"properties": {
				"linkedServiceName": {
					"referenceName": "AzureBlobStorage1",
					"type": "LinkedServiceReference"
				},
				"annotations": [],
				"type": "DelimitedText",
				"typeProperties": {
					"location": {
						"type": "AzureBlobStorageLocation",
						"fileName": "config.txt",
						"folderPath": "filefolder",
						"container": "development"
					},
					"columnDelimiter": ",",
					"escapeChar": "\\",
					"firstRowAsHeader": true,
					"quoteChar": "\""
				},
				"schema": []
			},
			"dependsOn": []
		},
		{
			"name": "[concat(parameters('factoryName'), '/DelimitedText22')]",
			"type": "Microsoft.DataFactory/factories/datasets",
			"apiVersion": "2018-06-01",
			"properties": {
				"linkedServiceName": {
					"referenceName": "AzureBlobStorage1",
					"type": "LinkedServiceReference"
				},
				"parameters": {
					"filename": {
						"type": "string"
					}
				},
				"annotations": [],
				"type": "DelimitedText",
				"typeProperties": {
					"location": {
						"type": "AzureBlobStorageLocation",
						"fileName": {
							"value": "@dataset().filename",
							"type": "Expression"
						},
						"folderPath": "filefolder/files",
						"container": "development"
					},
					"columnDelimiter": ",",
					"escapeChar": "\\",
					"firstRowAsHeader": true,
					"quoteChar": "\""
				},
				"schema": []
			},
			"dependsOn": []
		}
	]
}